{
  "BatchSize": 4,
  "SerializedLayers": [
    {
      "Type": "L2Penalty",
      "UnderlyingSerializedLayer": {
        "Bias": [
          0.0008780810701801945,
          -0.000886785549025438,
          0.0008671240254610206,
          0.0007799630116212459
        ],
        "Weights": [
          [
            4.927199173757763E-24,
            -4.9463559594940825E-24,
            5.3248754159888024E-24,
            5.195663802179199E-24
          ],
          [
            4.011377623558913E-25,
            -4.0263965452145135E-25,
            4.342060045742188E-25,
            4.2437539402240855E-25
          ],
          [
            6.1347227370334586E-24,
            -6.158887575041864E-24,
            6.624347514757206E-24,
            6.4596775229820754E-24
          ],
          [
            1.4878285747409964E-26,
            -1.4936340771913777E-26,
            1.6057491852747155E-26,
            1.5664121011086972E-26
          ],
          [
            6.930204656869902E-26,
            -6.959377283219545E-26,
            7.450971667134001E-26,
            7.24236978079913E-26
          ],
          [
            1.3613999052283046E-27,
            -1.3665475068384175E-27,
            1.4721784634129916E-27,
            1.4381752735601308E-27
          ],
          [
            1.6891083118731126E-26,
            -1.6957855517962832E-26,
            1.8213237654199114E-26,
            1.775614268234247E-26
          ]
        ],
        "ActivatorType": "Tanh",
        "GradientAdjustmentParameters": {
          "LearningRate": 1.0,
          "Type": "Momentum"
        },
        "Type": "Standard"
      },
      "PenaltyCoefficient": 0.3
    },
    {
      "Type": "L2Penalty",
      "UnderlyingSerializedLayer": {
        "Bias": [
          -0.7082389326264001,
          0.23643942307447047
        ],
        "Weights": [
          [
            -8.015382459431154E-15,
            4.138738361229479E-15
          ],
          [
            8.089226996836032E-15,
            -4.181395896088392E-15
          ],
          [
            -8.02549848821079E-15,
            4.12350403360356E-15
          ],
          [
            -7.303354780529717E-15,
            3.696625832761776E-15
          ]
        ],
        "ActivatorType": "Tanh",
        "GradientAdjustmentParameters": {
          "LearningRate": 1.0,
          "Type": "FixedLearningRate"
        },
        "Type": "Standard"
      },
      "PenaltyCoefficient": 0.3
    },
    {
      "Type": "L2Penalty",
      "UnderlyingSerializedLayer": {
        "Bias": [
          8.205907322432376
        ],
        "Weights": [
          [
            -1.9833449012874964E-06
          ],
          [
            1.1247408270101498E-06
          ]
        ],
        "ActivatorType": "Tanh",
        "GradientAdjustmentParameters": {
          "LearningRate": 1.0,
          "Type": "FixedLearningRate"
        },
        "Type": "Standard"
      },
      "PenaltyCoefficient": 0.5
    }
  ]
}